{   
    "singup": {
      "id": "singup",
      "type": "object",
      "properties": {
        "name": {
            "type": ["string"],            
            "required": true,
            "minLength": 5
          },
        "email": {
          "type": "string",
          "format": "email",
          "required": true         
        },
        "password": {
          "type": "string",
          "required": true,
          "minLength": 5
        }
      }
    },
    "singin": {
        "id": "singin",
        "type": "object",
        "properties": {         
          "email": {
            "type": "string",
            "format": "email",
            "required": true         
          },
          "password": {
            "type": "string",
            "required": true,
            "minLength": 5
          }
        }
    }  
}
  